{
  "accountAssociation": {
    "header": "",
    "payload": "",
    "signature": ""
  },
  "miniapp": {
    "version": "1",
    "name": "BlockTodo",
    "subtitle": "Chain-backed task keeping on Base",
    "description": "Write it down, stamp it on Base, and manage your task list from a wallet-ready mini app.",
    "tagline": "Chain-backed task keeping",
    "primaryCategory": "productivity",
    "tags": ["base", "todo", "productivity", "onchain"],
    "homeUrl": "https://blocktodo-base-miniapp.vercel.app",
    "canonicalDomain": "blocktodo-base-miniapp.vercel.app",
    "iconUrl": "https://blocktodo-base-miniapp.vercel.app/icon.svg",
    "splashImageUrl": "https://blocktodo-base-miniapp.vercel.app/icon.svg",
    "splashBackgroundColor": "#f2e6cf",
    "heroImageUrl": "https://blocktodo-base-miniapp.vercel.app/og-image.svg",
    "ogTitle": "BlockTodo",
    "ogDescription": "Write it down, stamp it on Base, and keep your tasks close.",
    "ogImageUrl": "https://blocktodo-base-miniapp.vercel.app/og-image.svg",
    "screenshotUrls": [
      "https://blocktodo-base-miniapp.vercel.app/og-image.svg"
    ],
    "requiredChains": ["eip155:8453"],
    "requiredCapabilities": ["wallet.getEthereumProvider"]
  }
}
